{
  "project_info": {
    "project_number": "636383616502",
    "firebase_url": "https://applicenta-8582b-default-rtdb.europe-west1.firebasedatabase.app",
    "project_id": "applicenta-8582b",
    "storage_bucket": "applicenta-8582b.appspot.com"
  },
  "client": [
    {
      "client_info": {
        "mobilesdk_app_id": "1:636383616502:android:e0cd754e9e649849a9bbd7",
        "android_client_info": {
          "package_name": "com.example.meplusplus"
        }
      },
      "oauth_client": [
        {
          "client_id": "636383616502-dgoepja0l2m8jpaq6knbideujuu5idco.apps.googleusercontent.com",
          "client_type": 1,
          "android_info": {
            "package_name": "com.example.meplusplus",
            "certificate_hash": "488bfcfc747f5c2d0110b7453a2002d67ad6d4f7"
          }
        },
        {
          "client_id": "636383616502-p6jufrendeotds8j9akgihvsg1mpr761.apps.googleusercontent.com",
          "client_type": 3
        }
      ],
      "api_key": [
        {
          "current_key": "AIzaSyDUwLMumKKMQ5Hh4EtBPDKNElKJF_B7Bjo"
        }
      ],
      "services": {
        "appinvite_service": {
          "other_platform_oauth_client": [
            {
              "client_id": "636383616502-p6jufrendeotds8j9akgihvsg1mpr761.apps.googleusercontent.com",
              "client_type": 3
            }
          ]
        }
      }
    }
  ],
  "configuration_version": "1"
}